<?xml version="1.0"?><npc name="Kirby Centrella" floorchange="0" walkinterval="3661"><health now="100" max="100"/> <look type="1203" head="38" body="197" legs="151" feet="247" addons="2"/> <interaction range="3" idletime="60"><interact keywords="hi" focus="1"><keywords>hello</keywords><keywords>oi</keywords><keywords>ola</keywords><response text="Yawn! When JIGGLYPUFF sings, POKEMON get drowsy... ...Me too... Snore..."><action name="idle" value="1"/></response></interact><interact keywords="bye" focus="0"><keywords>farewell</keywords><response text="Bye!"/></interact></interaction></npc>