<?xml version="1.0" encoding="UTF-8"?>
<monster name="Xatu" nameDescription="a Xatu" race="blood" experience="12" speed="295" manacost="0" minLevel="40" maxLevel="50">
	<health now="65" max="65"/>
	<type first="14" second="3"/> <!-- 20 = NULO sem img -->
	<look type="979" head="0" body="0" legs="0" feet="0" corpse="17567"/>
	<targetchange interval="5000" chance="8"/>
	<strategy attack="100" defense="0"/>
	<flags>
		<flag summonable="0"/>
		<flag attackable="1"/>
		<flag hostile="1"/>
		<flag illusionable="1"/>
		<flag convinceable="1"/>
		<flag pushable="1"/>
		<flag canpushitems="1"/>
		<flag canpushcreatures="0"/>
		<flag targetdistance="0"/>
		<flag staticattack="90"/>
		<flag runonhealth="0"/>
	</flags>
	<attacks>
		<attack name="melee" interval="1052" skill="24" attack="75"/>
		<attack name="Moves" interval="500"/>
		<attack name="Berries" inverval="60000" chance="1" target="1"/>
	</attacks>
	<defenses armor="10" defense="70"/>
	<elements>
	</elements>
	<voices interval="5000" chance="10">
		<voice sentence="XAATTUUU!"/>
	</voices>
	
<loot><item id="12142" countmax="1" chance="55555"/><item id="14469" countmax="4" chance="83333"/><item id="14478" countmax="1" chance="25000"/><item id="14512" countmax="1" chance="16666"/><item id="14518" countmax="1" chance="50000"/><item id="17804" countmax="1" chance="5000"/><item id="17807" countmax="1" chance="5000"/><item id="12233" countmax="1" chance="50"/><item id="18081" countmax="1" chance="50"/><item id="14464" countmax="5" chance="5000"/><item id="17978" countmax="1" chance="100"/><item id="17363" countmax="1" chance="10"/><item id="23526" countmax="1" chance="10"/><item id="23531" countmax="1" chance="10"/></loot></monster>
